HISTORY.rst
LICENSE
pipelog/__init__.py
pipelog/custom_agg_funcs.py
pipelog/frame_log.py
pipelog/pipe_tracker.py
pipelog-0.0.2.dist-info/LICENSE
pipelog-0.0.2.dist-info/WHEEL
pipelog-0.0.2.dist-info/METADATA
pipelog-0.0.2.dist-info/RECORD
